{   
    "name": "cardsupport-v2",   
    "title": "cardsupport-v2",   
    "description": "Card Support (Rewritten!)",   
    "author": "Norc and SpacemanDev",
    "version": "2.0",
    "minimumCoreVersion": "0.7.9",
    "compatibleCoreVersion":"0.7.9",
    "esmodules": [
      "index.js"
      ],
    "languages": [
      {
        "lang": "en",
        "name": "English",
        "path": "lang/en.json"
      }],
    "styles": [
      "./css/cardsupport-v2.css"
      ],
    "manifest": "https://raw.githubusercontent.com/Norc/cardsupport-v2/master/module.json",
    "download": "https://github.com/Norc/cardsupport-v2/archive/v2.0.zip",
    "url": "https://github.com/Norc/cardsupport-v2"
  }